{"lat":39.99,"lon":-86.13,"timezone":"America/Indiana/Indianapolis","timezone_offset":-18000,"current":{"dt":1604687664,"sunrise":1604665194,"sunset":1604702188,"temp":293.91,"feels_like":290.32,"pressure":1024,"humidity":45,"dew_point":281.56,"uvi":2.72,"clouds":1,"visibility":10000,"wind_speed":4.6,"wind_deg":210,"weather":[{"id":800,"main":"Clear","description":"clear sky","icon":"01d"}]},"minutely":[{"dt":1604687700,"precipitation":0},{"dt":1604687760,"precipitation":0},{"dt":1604687820,"precipitation":0},{"dt":1604687880,"precipitation":0},{"dt":1604687940,"precipitation":0},{"dt":1604688000,"precipitation":0},{"dt":1604688060,"precipitation":0},{"dt":1604688120,"precipitation":0},{"dt":1604688180,"precipitation":0},{"dt":1604688240,"precipitation":0},{"dt":1604688300,"precipitation":0},{"dt":1604688360,"precipitation":0},{"dt":1604688420,"precipitation":0},{"dt":1604688480,"precipitation":0},{"dt":1604688540,"precipitation":0},{"dt":1604688600,"precipitation":0},{"dt":1604688660,"precipitation":0},{"dt":1604688720,"precipitation":0},{"dt":1604688780,"precipitation":0},{"dt":1604688840,"precipitation":0},{"dt":1604688900,"precipitation":0},{"dt":1604688960,"precipitation":0},{"dt":1604689020,"precipitation":0},{"dt":1604689080,"precipitation":0},{"dt":1604689140,"precipitation":0},{"dt":1604689200,"precipitation":0},{"dt":1604689260,"precipitation":0},{"dt":1604689320,"precipitation":0},{"dt":1604689380,"precipitation":0},{"dt":1604689440,"precipitation":0},{"dt":1604689500,"precipitation":0},{"dt":1604689560,"precipitation":0},{"dt":1604689620,"precipitation":0},{"dt":1604689680,"precipitation":0},{"dt":1604689740,"precipitation":0},{"dt":1604689800,"precipitation":0},{"dt":1604689860,"precipitation":0},{"dt":1604689920,"precipitation":0},{"dt":1604689980,"precipitation":0},{"dt":1604690040,"precipitation":0},{"dt":1604690100,"precipitation":0},{"dt":1604690160,"precipitation":0},{"dt":1604690220,"precipitation":0},{"dt":1604690280,"precipitation":0},{"dt":1604690340,"precipitation":0},{"dt":1604690400,"precipitation":0},{"dt":1604690460,"precipitation":0},{"dt":1604690520,"precipitation":0},{"dt":1604690580,"precipitation":0},{"dt":1604690640,"precipitation":0},{"dt":1604690700,"precipitation":0},{"dt":1604690760,"precipitation":0},{"dt":1604690820,"precipitation":0},{"dt":1604690880,"precipitation":0},{"dt":1604690940,"precipitation":0},{"dt":1604691000,"precipitation":0},{"dt":1604691060,"precipitation":0},{"dt":1604691120,"precipitation":0},{"dt":1604691180,"precipitation":0},{"dt":1604691240,"precipitation":0},{"dt":1604691300,"precipitation":0}],"hourly":[{"dt":1604685600,"temp":293.91,"feels_like":290.68,"pressure":1024,"humidity":45,"dew_point":281.56,"clouds":1,"visibility":10000,"wind_speed":4.09,"wind_deg":207,"weather":[{"id":800,"main":"Clear","description":"clear sky","icon":"01d"}],"pop":0},{"dt":1604689200,"temp":293.25,"feels_like":289.96,"pressure":1024,"humidity":47,"dew_point":281.6,"clouds":1,"visibility":10000,"wind_speed":4.19,"wind_deg":210,"weather":[{"id":800,"main":"Clear","description":"clear sky","icon":"01d"}],"pop":0},{"dt":1604692800,"temp":293.02,"feels_like":289.8,"pressure":1023,"humidity":48,"dew_point":281.7,"clouds":0,"visibility":10000,"wind_speed":4.12,"wind_deg":215,"weather":[{"id":800,"main":"Clear","description":"clear sky","icon":"01d"}],"pop":0},{"dt":1604696400,"temp":292.43,"feels_like":289.6,"pressure":1023,"humidity":50,"dew_point":281.76,"clouds":0,"visibility":10000,"wind_speed":3.59,"wind_deg":215,"weather":[{"id":800,"main":"Clear","description":"clear sky","icon":"01d"}],"pop":0},{"dt":1604700000,"temp":290.49,"feels_like":288.19,"pressure":1023,"humidity":57,"dew_point":281.9,"clouds":0,"visibility":10000,"wind_speed":2.88,"wind_deg":213,"weather":[{"id":800,"main":"Clear","description":"clear sky","icon":"01d"}],"pop":0},{"dt":1604703600,"temp":288.61,"feels_like":286.24,"pressure":1023,"humidity":62,"dew_point":281.51,"clouds":0,"visibility":10000,"wind_speed":2.8,"wind_deg":205,"weather":[{"id":800,"main":"Clear","description":"clear sky","icon":"01n"}],"pop":0},{"dt":1604707200,"temp":287.92,"feels_like":285.52,"pressure":1024,"humidity":65,"dew_point":281.54,"clouds":0,"visibility":10000,"wind_speed":2.85,"wind_deg":200,"weather":[{"id":800,"main":"Clear","description":"clear sky","icon":"01n"}],"pop":0},{"dt":1604710800,"temp":287.34,"feels_like":284.77,"pressure":1024,"humidity":67,"dew_point":281.52,"clouds":0,"visibility":10000,"wind_speed":3.06,"wind_deg":197,"weather":[{"id":800,"main":"Clear","description":"clear sky","icon":"01n"}],"pop":0},{"dt":1604714400,"temp":286.82,"feels_like":284.08,"pressure":1024,"humidity":70,"dew_point":281.49,"clouds":0,"visibility":10000,"wind_speed":3.35,"wind_deg":194,"weather":[{"id":800,"main":"Clear","description":"clear sky","icon":"01n"}],"pop":0},{"dt":1604718000,"temp":286.34,"feels_like":283.42,"pressure":1024,"humidity":71,"dew_point":281.35,"clouds":0,"visibility":10000,"wind_speed":3.53,"wind_deg":194,"weather":[{"id":800,"main":"Clear","description":"clear sky","icon":"01n"}],"pop":0},{"dt":1604721600,"temp":285.82,"feels_like":283.01,"pressure":1024,"humidity":72,"dew_point":281.08,"clouds":0,"visibility":10000,"wind_speed":3.27,"wind_deg":194,"weather":[{"id":800,"main":"Clear","description":"clear sky","icon":"01n"}],"pop":0},{"dt":1604725200,"temp":285.35,"feels_like":282.67,"pressure":1024,"humidity":74,"dew_point":280.87,"clouds":0,"visibility":10000,"wind_speed":3.07,"wind_deg":196,"weather":[{"id":800,"main":"Clear","description":"clear sky","icon":"01n"}],"pop":0},{"dt":1604728800,"temp":284.9,"feels_like":282.41,"pressure":1024,"humidity":76,"dew_point":280.84,"clouds":0,"visibility":10000,"wind_speed":2.78,"wind_deg":196,"weather":[{"id":800,"main":"Clear","description":"clear sky","icon":"01n"}],"pop":0},{"dt":1604732400,"temp":284.49,"feels_like":282.14,"pressure":1024,"humidity":77,"dew_point":280.77,"clouds":0,"visibility":10000,"wind_speed":2.51,"wind_deg":197,"weather":[{"id":800,"main":"Clear","description":"clear sky","icon":"01n"}],"pop":0},{"dt":1604736000,"temp":284.15,"feels_like":281.8,"pressure":1025,"humidity":79,"dew_point":280.71,"clouds":0,"visibility":10000,"wind_speed":2.53,"wind_deg":194,"weather":[{"id":800,"main":"Clear","description":"clear sky","icon":"01n"}],"pop":0},{"dt":1604739600,"temp":283.81,"feels_like":281.39,"pressure":1025,"humidity":80,"dew_point":280.54,"clouds":0,"visibility":10000,"wind_speed":2.57,"wind_deg":187,"weather":[{"id":800,"main":"Clear","description":"clear sky","icon":"01n"}],"pop":0},{"dt":1604743200,"temp":283.5,"feels_like":281.11,"pressure":1025,"humidity":80,"dew_point":280.25,"clouds":0,"visibility":10000,"wind_speed":2.43,"wind_deg":184,"weather":[{"id":800,"main":"Clear","description":"clear sky","icon":"01n"}],"pop":0},{"dt":1604746800,"temp":283.23,"feels_like":280.74,"pressure":1025,"humidity":79,"dew_point":279.93,"clouds":0,"visibility":10000,"wind_speed":2.43,"wind_deg":183,"weather":[{"id":800,"main":"Clear","description":"clear sky","icon":"01n"}],"pop":0},{"dt":1604750400,"temp":282.94,"feels_like":280.4,"pressure":1026,"humidity":79,"dew_point":279.57,"clouds":0,"visibility":10000,"wind_speed":2.42,"wind_deg":187,"weather":[{"id":800,"main":"Clear","description":"clear sky","icon":"01n"}],"pop":0},{"dt":1604754000,"temp":283.15,"feels_like":280.51,"pressure":1026,"humidity":77,"dew_point":279.44,"clouds":0,"visibility":10000,"wind_speed":2.51,"wind_deg":186,"weather":[{"id":800,"main":"Clear","description":"clear sky","icon":"01d"}],"pop":0},{"dt":1604757600,"temp":285.06,"feels_like":282.28,"pressure":1026,"humidity":69,"dew_point":279.58,"clouds":0,"visibility":10000,"wind_speed":2.79,"wind_deg":189,"weather":[{"id":800,"main":"Clear","description":"clear sky","icon":"01d"}],"pop":0},{"dt":1604761200,"temp":286.84,"feels_like":283.97,"pressure":1026,"humidity":61,"dew_point":279.57,"clouds":0,"visibility":10000,"wind_speed":2.88,"wind_deg":189,"weather":[{"id":800,"main":"Clear","description":"clear sky","icon":"01d"}],"pop":0},{"dt":1604764800,"temp":288.71,"feels_like":285.78,"pressure":1025,"humidity":54,"dew_point":279.47,"clouds":0,"visibility":10000,"wind_speed":2.96,"wind_deg":187,"weather":[{"id":800,"main":"Clear","description":"clear sky","icon":"01d"}],"pop":0},{"dt":1604768400,"temp":290.27,"feels_like":287.28,"pressure":1025,"humidity":49,"dew_point":279.52,"clouds":0,"visibility":10000,"wind_speed":3.06,"wind_deg":189,"weather":[{"id":800,"main":"Clear","description":"clear sky","icon":"01d"}],"pop":0},{"dt":1604772000,"temp":291.54,"feels_like":288.5,"pressure":1024,"humidity":45,"dew_point":279.54,"clouds":0,"visibility":10000,"wind_speed":3.1,"wind_deg":196,"weather":[{"id":800,"main":"Clear","description":"clear sky","icon":"01d"}],"pop":0},{"dt":1604775600,"temp":292.39,"feels_like":289.4,"pressure":1024,"humidity":43,"dew_point":279.76,"clouds":0,"visibility":10000,"wind_speed":3.07,"wind_deg":201,"weather":[{"id":800,"main":"Clear","description":"clear sky","icon":"01d"}],"pop":0},{"dt":1604779200,"temp":292.61,"feels_like":289.73,"pressure":1023,"humidity":44,"dew_point":280.14,"clouds":0,"visibility":10000,"wind_speed":3.08,"wind_deg":200,"weather":[{"id":800,"main":"Clear","description":"clear sky","icon":"01d"}],"pop":0},{"dt":1604782800,"temp":292.33,"feels_like":289.96,"pressure":1023,"humidity":47,"dew_point":280.88,"clouds":0,"visibility":10000,"wind_speed":2.58,"wind_deg":197,"weather":[{"id":800,"main":"Clear","description":"clear sky","icon":"01d"}],"pop":0},{"dt":1604786400,"temp":290.34,"feels_like":288.52,"pressure":1023,"humidity":54,"dew_point":280.99,"clouds":0,"visibility":10000,"wind_speed":1.87,"wind_deg":185,"weather":[{"id":800,"main":"Clear","description":"clear sky","icon":"01d"}],"pop":0},{"dt":1604790000,"temp":288.46,"feels_like":286.43,"pressure":1023,"humidity":59,"dew_point":280.67,"clouds":0,"visibility":10000,"wind_speed":2.01,"wind_deg":178,"weather":[{"id":800,"main":"Clear","description":"clear sky","icon":"01n"}],"pop":0},{"dt":1604793600,"temp":287.76,"feels_like":285.71,"pressure":1024,"humidity":63,"dew_point":280.94,"clouds":0,"visibility":10000,"wind_speed":2.15,"wind_deg":172,"weather":[{"id":800,"main":"Clear","description":"clear sky","icon":"01n"}],"pop":0},{"dt":1604797200,"temp":287.26,"feels_like":285.01,"pressure":1024,"humidity":67,"dew_point":281.28,"clouds":0,"visibility":10000,"wind_speed":2.58,"wind_deg":167,"weather":[{"id":800,"main":"Clear","description":"clear sky","icon":"01n"}],"pop":0},{"dt":1604800800,"temp":286.86,"feels_like":284.37,"pressure":1025,"humidity":69,"dew_point":281.49,"clouds":0,"visibility":10000,"wind_speed":2.93,"wind_deg":167,"weather":[{"id":800,"main":"Clear","description":"clear sky","icon":"01n"}],"pop":0},{"dt":1604804400,"temp":286.46,"feels_like":284.03,"pressure":1025,"humidity":72,"dew_point":281.61,"clouds":0,"visibility":10000,"wind_speed":2.93,"wind_deg":169,"weather":[{"id":800,"main":"Clear","description":"clear sky","icon":"01n"}],"pop":0},{"dt":1604808000,"temp":286.05,"feels_like":283.79,"pressure":1025,"humidity":74,"dew_point":281.61,"clouds":0,"visibility":10000,"wind_speed":2.69,"wind_deg":170,"weather":[{"id":800,"main":"Clear","description":"clear sky","icon":"01n"}],"pop":0},{"dt":1604811600,"temp":285.77,"feels_like":283.43,"pressure":1025,"humidity":75,"dew_point":281.53,"clouds":0,"visibility":10000,"wind_speed":2.79,"wind_deg":175,"weather":[{"id":800,"main":"Clear","description":"clear sky","icon":"01n"}],"pop":0},{"dt":1604815200,"temp":285.54,"feels_like":283.18,"pressure":1025,"humidity":75,"dew_point":281.37,"clouds":0,"visibility":10000,"wind_speed":2.74,"wind_deg":176,"weather":[{"id":800,"main":"Clear","description":"clear sky","icon":"01n"}],"pop":0},{"dt":1604818800,"temp":285.36,"feels_like":283.08,"pressure":1025,"humidity":75,"dew_point":281.23,"clouds":0,"visibility":10000,"wind_speed":2.56,"wind_deg":170,"weather":[{"id":800,"main":"Clear","description":"clear sky","icon":"01n"}],"pop":0},{"dt":1604822400,"temp":285.26,"feels_like":282.95,"pressure":1025,"humidity":75,"dew_point":281.14,"clouds":0,"visibility":10000,"wind_speed":2.57,"wind_deg":165,"weather":[{"id":800,"main":"Clear","description":"clear sky","icon":"01n"}],"pop":0},{"dt":1604826000,"temp":285.16,"feels_like":283.05,"pressure":1025,"humidity":76,"dew_point":281.12,"clouds":0,"visibility":10000,"wind_speed":2.32,"wind_deg":163,"weather":[{"id":800,"main":"Clear","description":"clear sky","icon":"01n"}],"pop":0},{"dt":1604829600,"temp":285.21,"feels_like":283.1,"pressure":1025,"humidity":76,"dew_point":281.25,"clouds":0,"visibility":10000,"wind_speed":2.34,"wind_deg":163,"weather":[{"id":800,"main":"Clear","description":"clear sky","icon":"01n"}],"pop":0},{"dt":1604833200,"temp":285.23,"feels_like":283.14,"pressure":1025,"humidity":78,"dew_point":281.56,"clouds":0,"visibility":10000,"wind_speed":2.44,"wind_deg":162,"weather":[{"id":800,"main":"Clear","description":"clear sky","icon":"01n"}],"pop":0},{"dt":1604836800,"temp":285.26,"feels_like":283.09,"pressure":1026,"humidity":80,"dew_point":282,"clouds":0,"visibility":10000,"wind_speed":2.71,"wind_deg":163,"weather":[{"id":800,"main":"Clear","description":"clear sky","icon":"01n"}],"pop":0},{"dt":1604840400,"temp":285.66,"feels_like":283.44,"pressure":1026,"humidity":81,"dew_point":282.59,"clouds":0,"visibility":10000,"wind_speed":2.98,"wind_deg":163,"weather":[{"id":800,"main":"Clear","description":"clear sky","icon":"01d"}],"pop":0},{"dt":1604844000,"temp":287.69,"feels_like":285.29,"pressure":1026,"humidity":74,"dew_point":283.24,"clouds":0,"visibility":10000,"wind_speed":3.48,"wind_deg":167,"weather":[{"id":800,"main":"Clear","description":"clear sky","icon":"01d"}],"pop":0},{"dt":1604847600,"temp":289.48,"feels_like":286.98,"pressure":1026,"humidity":67,"dew_point":283.46,"clouds":0,"visibility":10000,"wind_speed":3.71,"wind_deg":164,"weather":[{"id":800,"main":"Clear","description":"clear sky","icon":"01d"}],"pop":0},{"dt":1604851200,"temp":291.14,"feels_like":288.78,"pressure":1026,"humidity":61,"dew_point":283.64,"clouds":0,"visibility":10000,"wind_speed":3.57,"wind_deg":163,"weather":[{"id":800,"main":"Clear","description":"clear sky","icon":"01d"}],"pop":0},{"dt":1604854800,"temp":292.83,"feels_like":290.43,"pressure":1026,"humidity":56,"dew_point":284.01,"clouds":0,"visibility":10000,"wind_speed":3.75,"wind_deg":168,"weather":[{"id":800,"main":"Clear","description":"clear sky","icon":"01d"}],"pop":0}],"daily":[{"dt":1604682000,"sunrise":1604665194,"sunset":1604702188,"temp":{"day":293.91,"min":283.33,"max":293.91,"night":286.82,"eve":289.21,"morn":283.33},"feels_like":{"day":290.68,"night":283.96,"eve":286.88,"morn":280.35},"pressure":1024,"humidity":45,"dew_point":281.56,"wind_speed":4.09,"wind_deg":207,"weather":[{"id":800,"main":"Clear","description":"clear sky","icon":"01d"}],"clouds":1,"pop":0,"uvi":2.72},{"dt":1604768400,"sunrise":1604751664,"sunset":1604788527,"temp":{"day":291.54,"min":282.94,"max":292.33,"night":286.46,"eve":287.76,"morn":282.94},"feels_like":{"day":288.5,"night":284.03,"eve":285.71,"morn":280.4},"pressure":1024,"humidity":45,"dew_point":279.54,"wind_speed":3.1,"wind_deg":196,"weather":[{"id":800,"main":"Clear","description":"clear sky","icon":"01d"}],"clouds":0,"pop":0,"uvi":2.9},{"dt":1604854800,"sunrise":1604838134,"sunset":1604874867,"temp":{"day":294.2,"min":285.16,"max":295.13,"night":289.37,"eve":290.87,"morn":285.26},"feels_like":{"day":292.19,"night":287.46,"eve":289.88,"morn":283.09},"pressure":1025,"humidity":55,"dew_point":284.89,"wind_speed":3.61,"wind_deg":179,"weather":[{"id":800,"main":"Clear","description":"clear sky","icon":"01d"}],"clouds":0,"pop":0,"uvi":2.87},{"dt":1604941200,"sunrise":1604924604,"sunset":1604961209,"temp":{"day":294.88,"min":286.78,"max":294.91,"night":290.81,"eve":291.29,"morn":286.78},"feels_like":{"day":292.81,"night":288.54,"eve":290.42,"morn":285.18},"pressure":1021,"humidity":63,"dew_point":287.78,"wind_speed":4.95,"wind_deg":202,"weather":[{"id":800,"main":"Clear","description":"clear sky","icon":"01d"}],"clouds":3,"pop":0,"uvi":3.05},{"dt":1605027600,"sunrise":1605011074,"sunset":1605047553,"temp":{"day":294.4,"min":288.71,"max":295.11,"night":292.32,"eve":293.79,"morn":288.71},"feels_like":{"day":290.34,"night":289.33,"eve":290.92,"morn":286.51},"pressure":1010,"humidity":63,"dew_point":287.15,"wind_speed":7.57,"wind_deg":184,"weather":[{"id":500,"main":"Rain","description":"light rain","icon":"10d"}],"clouds":50,"pop":0.32,"rain":0.32,"uvi":2.92},{"dt":1605114000,"sunrise":1605097545,"sunset":1605133898,"temp":{"day":283.08,"min":278.62,"max":284.48,"night":278.62,"eve":280.08,"morn":280.48},"feels_like":{"day":278.08,"night":275.28,"eve":276.45,"morn":276.08},"pressure":1014,"humidity":54,"dew_point":274.42,"wind_speed":4.54,"wind_deg":302,"weather":[{"id":501,"main":"Rain","description":"moderate rain","icon":"10d"}],"clouds":28,"pop":0.84,"rain":3.24,"uvi":2.47},{"dt":1605200400,"sunrise":1605184015,"sunset":1605220245,"temp":{"day":284.56,"min":276.38,"max":285.16,"night":280.95,"eve":281.54,"morn":276.38},"feels_like":{"day":280.05,"night":276.29,"eve":277.37,"morn":272.74},"pressure":1018,"humidity":43,"dew_point":270.29,"wind_speed":3.46,"wind_deg":111,"weather":[{"id":800,"main":"Clear","description":"clear sky","icon":"01d"}],"clouds":0,"pop":0,"uvi":2.45},{"dt":1605286800,"sunrise":1605270484,"sunset":1605306594,"temp":{"day":282.78,"min":277.06,"max":282.78,"night":277.06,"eve":278.55,"morn":279.06},"feels_like":{"day":277.79,"night":273.45,"eve":274.83,"morn":274.89},"pressure":1020,"humidity":58,"dew_point":275.05,"wind_speed":4.69,"wind_deg":349,"weather":[{"id":801,"main":"Clouds","description":"few clouds","icon":"02d"}],"clouds":23,"pop":0.18,"uvi":2.47}]}